willowlabs-0.8.0-py3.7-nspkg.pth
tests/__init__.py
tests/test_client.py
willowlabs/company_information/__init__.py
willowlabs/company_information/client.py
willowlabs/service_grpc/__init__.py
willowlabs/service_grpc/company_information/__init__.py
willowlabs/service_grpc/company_information/company_information_service_pb2.py
willowlabs/service_grpc/company_information/company_information_service_pb2_grpc.py
willowlabs/tools/__init__.py
willowlabs/tools/protobuffer_tools.py
willowlabs/tools/tools.py
willowlabs-0.8.0.dist-info/LICENSE
willowlabs-0.8.0.dist-info/METADATA
willowlabs-0.8.0.dist-info/WHEEL
willowlabs-0.8.0.dist-info/namespace_packages.txt
willowlabs-0.8.0.dist-info/top_level.txt
willowlabs-0.8.0.dist-info/RECORD
